src2txt/__init__.py
src2txt/main.py
src2txt-0.5.0.dist-info/LICENSE
src2txt-0.5.0.dist-info/METADATA
src2txt-0.5.0.dist-info/WHEEL
src2txt-0.5.0.dist-info/entry_points.txt
src2txt-0.5.0.dist-info/RECORD
