Metadata-Version: 2.1
Name: src2txt
Version: 0.5.0
Summary: A command-line tool to convert documents and web pages to text.
Author: Simon Engwerda
Author-email: simon@engwerda.net
Requires-Python: >=3.11,<4.0
Classifier: Programming Language :: Python :: 3
Classifier: Programming Language :: Python :: 3.11
Classifier: Programming Language :: Python :: 3.12
Requires-Dist: beautifulsoup4 (>=4.12.3,<5.0.0)
Requires-Dist: lxml-html-clean (>=0.1.1,<0.2.0)
Requires-Dist: pathspec (>=0.12.1,<0.13.0)
Requires-Dist: pymupdf (>=1.24.1,<2.0.0)
Requires-Dist: python-magic (>=0.4.27,<0.5.0)
Requires-Dist: readability-lxml (>=0.8.1,<0.9.0)
Requires-Dist: requests (>=2.31.0,<3.0.0)
Requires-Dist: typer (>=0.12.3,<0.13.0)
Project-URL: Homepage, https://github.com/engwerda/src2txt
